revoltbots/RBL.py
revoltbots/__init__.py
revoltbots.py-0.0.2.dist-info/LICENSE
revoltbots.py-0.0.2.dist-info/METADATA
revoltbots.py-0.0.2.dist-info/WHEEL
revoltbots.py-0.0.2.dist-info/top_level.txt
revoltbots.py-0.0.2.dist-info/RECORD
