Metadata-Version: 2.1
Name: revoltbots.py
Version: 0.0.2
Summary: A small package for the revoltbots api!
Author-email: Xynnix <admin@revoltbots.org>
Project-URL: Homepage, https://github.com/revoltbots/revoltbots.py
Project-URL: Bug Tracker, https://github.com/revoltbots/revoltbots.py/issues
License-File: LICENSE
